{
  "version": "2.50.1",
  "release_date": "2026-02-14",
  "release_name": "UI Cleanup & Bug Fixes",
  "download_url": "https://raw.githubusercontent.com/cfd2474/TAKNET-PS_ADS-B_Feeder/main/install/install.sh",
  "changelog_url": "https://raw.githubusercontent.com/cfd2474/TAKNET-PS_ADS-B_Feeder/main/CHANGELOG.md",
  "minimum_version": "2.40.0",
  "breaking_changes": false,
  "release_notes": "BUG FIX: Added missing version variable to feeds-account-required route, preventing 500 error when accessing Account-Required Feeds page. UI CLEANUP: Removed standalone 978 MHz UAT section from Settings page - now handled through SDR detection in Setup wizard. Simplifies configuration and eliminates duplicate controls."
}
